django_single_table_db_storage/__init__.py
django_single_table_db_storage/models.py
django_single_table_db_storage/storage.py
django_single_table_db_storage/urls.py
django_single_table_db_storage/views.py
django_single_table_db_storage/migrations/0001_initial.py
django_single_table_db_storage/migrations/__init__.py
django_single_table_db_storage-0.1.3.dist-info/LICENSE.md
django_single_table_db_storage-0.1.3.dist-info/METADATA
django_single_table_db_storage-0.1.3.dist-info/WHEEL
django_single_table_db_storage-0.1.3.dist-info/top_level.txt
django_single_table_db_storage-0.1.3.dist-info/RECORD
