Metadata-Version: 2.1
Name: django-single-table-db-storage
Version: 0.1.3
Summary: Provides a Django storage implementation that uses a single database table.
Home-page: https://github.com/waterimp/django-single-table-db-storage
Author: Lee Bush
License: MIT
Keywords: django storage database
Classifier: Development Status :: 4 - Beta
Classifier: Environment :: Web Environment
Classifier: Intended Audience :: Developers
Classifier: License :: OSI Approved :: MIT License
Classifier: Operating System :: OS Independent
Classifier: Natural Language :: English
Classifier: Programming Language :: Python
Classifier: Programming Language :: Python :: 3.5
Classifier: Programming Language :: Python :: Implementation :: CPython
Classifier: Framework :: Django
Classifier: Framework :: Django :: 3.2
Requires-Python: >=3.5
License-File: LICENSE.md
Requires-Dist: Django >=3.2
Requires-Dist: django-extensions >=3.2
